heat_helper/__init__.py
heat_helper/core.py
heat_helper/dates.py
heat_helper/duplicates.py
heat_helper/exceptions.py
heat_helper/matching.py
heat_helper/names.py
heat_helper/postcode.py
heat_helper/updates.py
heat_helper/utils.py
heat_helper/yeargroup.py
heat_helper-0.1.0.dist-info/licenses/LICENSE
heat_helper-0.1.0.dist-info/WHEEL
heat_helper-0.1.0.dist-info/METADATA
heat_helper-0.1.0.dist-info/RECORD
