Metadata-Version: 2.4
Name: heat_helper
Version: 0.1.0
Summary: A python library to help users of the Higher Education Access Tracker (HEAT) process their data.
Author: Hannah Merry
License-Expression: GPL-3.0-or-later
License-File: LICENSE
Requires-Dist: openpyxl>=3.1.5
Requires-Dist: pandas>=2.3.3
Requires-Dist: rapidfuzz>=3.14.3
Requires-Python: >=3.10
Project-URL: Documentation, https://hammezii.github.io/heat-helper/
Project-URL: Repository, https://github.com/hammezii/heat-helper
